{
  "_id": "f2984990747106d0",
  "name": "Iron Spirit Reversal",
  "type": "technique",
  "img": "icons/svg/aura.svg",
  "system": {
    "description": "Discipline: Neigong\nSkill: Muscle against opponent’s Parry\nType: Counter\nQi: 1\n\nYou assume a low and powerful stance, thrusting out your arms as you build your internal energy to reverse attacks made against your body. When someone attacks you with a melee weapon and misses, you push their weapon back upon them, causing them to be affected by their own attack. Roll Muscle against your opponent’s Parry applying a -1d10 Penalty to the Muscle roll for each Rank that your opponent’s Qi exceeds your own. On a Success the weapon strikes your opponent instead of you. This only works against Mundane Attacks. Cathartic: Works just like the normal version except you can reverse Kung Fu Techniques and mundane Attacks. This only works against opponents who have less Qi Ranks than you. This does not work against Neigong Techniques.",
    "source": "Wandering Heroes of Ogre Gate, Chapter 3: Kung Fu Techniques",
    "cost": "",
    "discipline": "neigong",
    "techniqueType": "counter",
    "activationSkill": "physical.muscle",
    "targetDefense": "none",
    "targetNumber": 6,
    "qiRank": 1,
    "attackModifier": 0,
    "catharticAttackModifier": 0,
    "damage": "",
    "damageModifier": 0,
    "catharticDamageModifier": 0,
    "directWounds": "",
    "totalSuccessDirectWounds": "",
    "catharticDirectWounds": "",
    "catharticTotalSuccessDirectWounds": "",
    "directWoundsNote": "",
    "targetDrains": "",
    "totalSuccessTargetDrains": "",
    "catharticTargetDrains": "",
    "catharticTotalSuccessTargetDrains": "",
    "targetDrainsNote": "",
    "targetEffects": "",
    "totalSuccessTargetEffects": "",
    "catharticTargetEffects": "",
    "catharticTotalSuccessTargetEffects": "",
    "targetEffectsNote": "",
    "selfWounds": 0,
    "catharticSelfWounds": 0,
    "catharticImbalanceMultiplier": 1,
    "consequenceNote": "",
    "openDamage": false,
    "catharticOpenDamage": false,
    "extraWounds": 0,
    "catharticExtraWounds": 0,
    "counter": "See description.",
    "secret": false,
    "accessNotes": "",
    "combination": false,
    "prerequisiteTechniques": "",
    "requirementNotes": "",
    "requiredFlaws": "",
    "requiredSkillRanks": "",
    "catharticEffect": "Works just like the normal version except you can reverse Kung Fu Techniques and mundane Attacks. This only works against opponents who have less Qi Ranks than you. This does not work against Neigong Techniques.",
    "formation": false,
    "formationParticipants": 0,
    "formationNotes": ""
  },
  "effects": [],
  "folder": "f268d40de59e0b3c",
  "flags": {
    "ogregatefoundry": {
      "chapter": 3,
      "rulesKey": "ironSpiritReversal",
      "originalDiscipline": "Neigong",
      "secret": false,
      "group": "neigong"
    }
  },
  "ownership": {
    "default": 0
  },
  "_stats": {
    "compendiumSource": "Item.f2984990747106d0",
    "duplicateSource": null,
    "exportSource": null,
    "coreVersion": "13.351",
    "systemId": "ogregatefoundry",
    "systemVersion": "0.1.6",
    "createdTime": 0,
    "modifiedTime": 0,
    "lastModifiedBy": null
  },
  "_key": "!items!f2984990747106d0"
}
