{
  "_id": "1c08a19d0aec3c6e",
  "name": "Rising Dragon Stance",
  "type": "technique",
  "img": "icons/svg/aura.svg",
  "system": {
    "description": "Discipline: None\nSkill: Endurance\nType: Stance (Formation)\nQi: 4\n\nThis stance requires six people, who must stack to form a three-tier pyramid. From this position they are well defended against Melee Attacks and can channel their efforts into attacks together as one. While in this stance all involved gain a 10 to Parry and Hardiness. Cathartic: This allows the participants to Attack as one if they choose. When doing so, one of the members of the formation attacks normally on ev eryone’s behalf (using a Technique or Combat Skill). This gives the attacker a +2d10 to his Attack roll and +4 Extra Wounds to Damage.",
    "source": "Wandering Heroes of Ogre Gate, Chapter 3: Kung Fu Techniques",
    "cost": "",
    "discipline": "none",
    "techniqueType": "stance",
    "activationSkill": "physical.endurance",
    "targetDefense": "none",
    "targetNumber": 6,
    "qiRank": 4,
    "attackModifier": 0,
    "catharticAttackModifier": 0,
    "damage": "",
    "damageModifier": 0,
    "catharticDamageModifier": 0,
    "directWounds": "",
    "totalSuccessDirectWounds": "",
    "catharticDirectWounds": "",
    "catharticTotalSuccessDirectWounds": "",
    "directWoundsNote": "",
    "targetDrains": "",
    "totalSuccessTargetDrains": "",
    "catharticTargetDrains": "",
    "catharticTotalSuccessTargetDrains": "",
    "targetDrainsNote": "",
    "targetEffects": "",
    "totalSuccessTargetEffects": "",
    "catharticTargetEffects": "",
    "catharticTotalSuccessTargetEffects": "",
    "targetEffectsNote": "",
    "selfWounds": 0,
    "catharticSelfWounds": 0,
    "catharticImbalanceMultiplier": 1,
    "consequenceNote": "",
    "openDamage": false,
    "catharticOpenDamage": false,
    "extraWounds": 0,
    "catharticExtraWounds": 0,
    "counter": "",
    "secret": false,
    "accessNotes": "",
    "combination": false,
    "prerequisiteTechniques": "",
    "requirementNotes": "",
    "requiredFlaws": "",
    "requiredSkillRanks": "",
    "catharticEffect": "This allows the participants to Attack as one if they choose. When doing so, one of the members of the formation attacks normally on ev eryone’s behalf (using a Technique or Combat Skill). This gives the attacker a +2d10 to his Attack roll and +4 Extra Wounds to Damage.",
    "formation": true,
    "formationParticipants": 6,
    "formationNotes": "Requires at least 6 participants. Formation can be broken by a Total Success attack against it."
  },
  "effects": [],
  "folder": "bbf521064c78fda1",
  "flags": {
    "ogregatefoundry": {
      "chapter": 3,
      "rulesKey": "risingDragonStance",
      "originalDiscipline": "None",
      "secret": false,
      "group": "stance"
    }
  },
  "ownership": {
    "default": 0
  },
  "_stats": {
    "compendiumSource": "Item.1c08a19d0aec3c6e",
    "duplicateSource": null,
    "exportSource": null,
    "coreVersion": "13.351",
    "systemId": "ogregatefoundry",
    "systemVersion": "0.1.6",
    "createdTime": 0,
    "modifiedTime": 0,
    "lastModifiedBy": null
  },
  "_key": "!items!1c08a19d0aec3c6e"
}
