{
  "_id": "508b029bc845f2f0",
  "name": "Palanquin",
  "type": "equipment",
  "img": "icons/environment/settlement/wagon.webp",
  "system": {
    "description": "Mount or transport entry from the Chapter 5 Mounts and Transports table.",
    "source": "Wandering Heroes of Ogre Gate, Chapter 5: Equipment and Goods",
    "cost": "2000 to 150,000",
    "category": "mountTransport",
    "quantity": 1,
    "weight": "",
    "performanceRating": 4,
    "handlingSpeed": "9 MPH",
    "milesPerDay": "10",
    "speedScore": "2d10",
    "evade": 3,
    "hardiness": 3,
    "integrity": 1,
    "damage": "None"
  },
  "effects": [],
  "folder": "d1c2298b8cf6dda7",
  "flags": {
    "ogregatefoundry": {
      "categoryLabel": "Mount or Transport"
    }
  },
  "ownership": {
    "default": 0
  },
  "_key": "!items!508b029bc845f2f0"
}
